{
  "resourceType": "ClinicalUseDefinition",
  "id": "db12161-tardive-dyskinesia-(disease)",
  "type": "indication",
  "subject": [
    {
      "reference": "MedicationKnowledge/db12161"
    }
  ],
  "indication": {
    "diseaseSymptomProcedure": {
      "concept": {
        "text": "tardive dyskinesia (disease)"
      }
    }
  },
  "extension": [
    {
      "url": "https://notxgnn.yao.care/fhir/StructureDefinition/evidence-level",
      "valueCode": "L5"
    },
    {
      "url": "https://notxgnn.yao.care/fhir/StructureDefinition/txgnn-score",
      "valueDecimal": 0.5
    }
  ]
}