{
  "resourceType": "ClinicalUseDefinition",
  "id": "db15066-hepatic-porphyria",
  "type": "indication",
  "subject": [
    {
      "reference": "MedicationKnowledge/db15066"
    }
  ],
  "indication": {
    "diseaseSymptomProcedure": {
      "concept": {
        "text": "hepatic porphyria"
      }
    }
  },
  "extension": [
    {
      "url": "https://notxgnn.yao.care/fhir/StructureDefinition/evidence-level",
      "valueCode": "L5"
    },
    {
      "url": "https://notxgnn.yao.care/fhir/StructureDefinition/txgnn-score",
      "valueDecimal": 0.5
    }
  ]
}